alu.v
module  alu(A,B,O,CTR,ck);
input	[7:0]	A, B;
input	[3:0]	CTR;
input	ck;
output	[7:0] O;
reg	[7:0]	INA, INB, O;
reg	[3:0]	C;
wire	[7:0]	OUT;

always @(posedge ck) begin
    C <= CTR;
    INA <= A;
    INB <= B;
    case (C)
    'b0000 : O <= INA + INB;
    'b0001 : O <= INA - INB;
    'b1000 : O <= INA & INB;
    'b1001 : O <= INA | INB;
    'b1010 : O <= INA ^ INB;
    'b1011 : O <= ~INA;
    'b1100 : O<=INA>>1;
    'b1101 : O<=INA<<1;
    'b1110 : O<={INA[0],INA[7:1]};
    'b1111 : O<={INA[6:0],INA[7]};
    default : O<=0;
    endcase
end
endmodule

alu_test.v
module  alutest;
reg	[7:0]	A, B;
reg	[3:0]	CTR;
reg	ck;
wire	[7:0] O0;
initial begin
	ck=0;
	$dumpfile("alu.vcd");
	$dumpvars;
//	$monitor( "%t\tA=%h, B=%h, CTR=%h, OUT=%h", $time, A, B, CTR, O );
   #1000
     $display( "OK\n" );
   $finish;
end
alu	ALU(A , B , O0 , CTR , ck);
always	#10	ck = ~ck;
always @(negedge ck) begin
	A = $random;
	B = $random;
	CTR  = $random;
end

   reg	[7:0]	INA, INB, OUT, O;
reg	[3:0]	C, CC;

always @(negedge ck) begin
   if( !(O == O0 || ( (CC == 'b0010 || CC== 'b0011 || CC == 'b0100 || CC == 'b0101 || CC=='b0110 || CC == 'b0111) && O0 == 8'b0)) ) $finish;
  

end
always @(posedge ck) begin
	C <= CTR;	
   CC <= C;
	INA <= A;
	INB <= B;
	O <= OUT;
end

always @(C or INA or INB) begin
	case  (C)
	'b0000 : OUT <= INA + INB;
	'b0001 : OUT <= INA - INB;
	'b1000 : OUT <= INA & INB;
	'b1001 : OUT <= INA | INB;
	'b1010 : OUT <= INA ^ INB;
	'b1011 : OUT <= ~INA;
	'b1100 : OUT <= INA>>1;
	'b1101 : OUT <= INA<<1;
	'b1110 : OUT <= {INA[0], INA[7:1]};
	'b1111 : OUT <= {INA[6:0], INA[7]};
//	  default : OUT <= 0;
	endcase
end


endmodule

alu.vcd
$date
	Fri Apr 21 12:13:11 2023
$end
$version
	Icarus Verilog
$end
$timescale
	1s
$end
$scope module alutest $end
$var wire 8 ! O0 [7:0] $end
$var reg 8 " A [7:0] $end
$var reg 8 # B [7:0] $end
$var reg 4 $ C [3:0] $end
$var reg 4 % CC [3:0] $end
$var reg 4 & CTR [3:0] $end
$var reg 8 ' INA [7:0] $end
$var reg 8 ( INB [7:0] $end
$var reg 8 ) O [7:0] $end
$var reg 8 * OUT [7:0] $end
$var reg 1 + ck $end
$scope module ALU $end
$var wire 8 , A [7:0] $end
$var wire 8 - B [7:0] $end
$var wire 4 . CTR [3:0] $end
$var wire 1 + ck $end
$var reg 4 / C [3:0] $end
$var reg 8 0 INA [7:0] $end
$var reg 8 1 INB [7:0] $end
$var reg 8 2 O [7:0] $end
$upscope $end
$upscope $end
$enddefinitions $end
#0
$dumpvars
bx 2
bx 1
bx 0
bx /
bx .
bx -
bx ,
0+
bx *
bx )
bx (
bx '
bx &
bx %
bx $
bx #
bx "
bx !
$end
#10
b0 !
b0 2
1+
#20
b1001 &
b1001 .
b10000001 #
b10000001 -
b100100 "
b100100 ,
0+
#30
b10100101 *
b10000001 (
b100100 '
b1001 $
b10000001 1
b100100 0
b1001 /
1+
#40
b1101 &
b1101 .
b1101 #
b1101 -
b1100011 "
b1100011 ,
0+
#50
b11000110 *
b10100101 !
b10100101 2
b1101 1
b1100011 0
b1101 /
b10100101 )
b1101 (
b1100011 '
b1001 %
b1101 $
1+
#60
b1 &
b1 .
b10010 #
b10010 -
b1100101 "
b1100101 ,
0+
#70
b1010011 *
b11000110 )
b10010 (
b1100101 '
b1101 %
b1 $
b0 !
b0 2
b10010 1
b1100101 0
b1 /
1+
#80
b1101 &
b1101 .
b1110110 #
b1110110 -
b1101 "
b1101 ,
0+
