mul2.v
module mul(A,B,O,ck,start,fin);
input [7:0] A, B;
input ck,start;
output [16:0] O;

reg [4:0] st;
reg [7:0] AIN, BIN;
reg [16:0] O;

always @(posedge ck) begin
    if (start) begin
        AIN <= A;
        BIN <= B;
        st <= 0;
    end 
    else begin
        case (st)
        0: begin
            O <= O + (AIN & 1 ? BIN : 0);
            AIN<=(AIN>>1);
            st <= 1;
            end
        1: begin
            O <= (O<<1) + (AIN & 1 ? BIN : 0);
            AIN<=(AIN>>1);
            st <= 2;
            end
        2: begin
            O <= (O<<1) + (AIN & 1 ? BIN : 0);
            AIN <= (AIN >>1);
            st <= 3;
            end
        3: begin
            O <= (O<<1) + (AIN & 1 ? BIN : 0);
            AIN <= (AIN >>1);
            st <= 4;
            end
        4: begin
            O <= (O<<1) + (AIN & 1 ? BIN : 0);
            AIN <= (AIN >>1);
            st <= 5;
            end
        5: begin
            O <= (O<<1) + (AIN & 1 ? BIN : 0);
            AIN <= (AIN >>1);
            st <= 6;
            end
        6: begin
            O <= (O<<1) + (AIN & 1 ? BIN : 0);
            AIN <= (AIN >>1);
            st<=7;
            end
        7: begin
            O <= (O<<1) + (AIN & 1 ? BIN : 0);
            st<=0;
            end
        default: begin
            st <= 0;
    endcase
  end
end
endmodule

mul000_test.v
module  multest;
reg	[7:0]	A, B;
reg	ck;
reg	start;
reg	[3:0] st;
wire	[16:0] O;
reg	[16:0] OR;
initial begin
	ck=0;
	start=0;
	st=0;
	$dumpfile("mul.vcd");
	$dumpvars;
	A=0;
	B=0;
end
mul	MUL(A , B , O ,  ck, start,fin);
always	#10	ck = ~ck;
always @(negedge ck) begin
	if( st == 0 ) begin
	    start <= 1;
	end
	else start <= 0;
	if( fin == 1 ) begin
	    OR <= O;
	    {B,A} <= {B,A} + 1;
	   st <= 0;
            if( O != A*B ) begin
                  $finish;
            end
            if( A == 'h f && B == 'h f ) begin
               $display( "OK\n" );
               $finish;
            end
	end else  st <= st+1;
end
endmodule

dump.vcd
$date
	Tue Apr 25 12:18:50 2023
$end
$version
	Icarus Verilog
$end
$timescale
	1s
$end
$scope module multest $end
$var wire 1 ! fin $end
$var wire 17 " O [16:0] $end
$var reg 8 # A [7:0] $end
$var reg 8 $ B [7:0] $end
$var reg 17 % OR [16:0] $end
$var reg 1 & ck $end
$var reg 4 ' st [3:0] $end
$var reg 1 ( start $end
$scope module MUL $end
$var wire 8 ) A [7:0] $end
$var wire 8 * B [7:0] $end
$var wire 1 & ck $end
$var wire 1 ( start $end
$var reg 8 + AIN [7:0] $end
$var reg 8 , BIN [7:0] $end
$var reg 17 - O [16:0] $end
$var reg 1 ! fin $end
$var reg 5 . st [4:0] $end
$upscope $end
$upscope $end
$enddefinitions $end
#0
$dumpvars
bx .
bx -
bx ,
bx +
b0 *
b0 )
0(
b0 '
0&
bx %
b0 $
b0 #
bx "
x!
$end
#10
0!
b0 .
1&
#20
b1 '
1(
0&
#30
b0 ,
b0 +
1&
#40
b10 '
0(
0&
#50
b1 .
b0 "
b0 -
1&
#60
b11 '
0&
#70
b10 .
1&
#80
b100 '
0&
#90
b11 .
1&
#100
b101 '
0&
#110
b100 .
1&
#120
b110 '
0&
#130
b101 .
1&
#140
b111 '
0&
#150
b110 .
1&
#160
b1000 '
0&
#170
b111 .
1&
#180
b1001 '
0&
#190
1!
1&
#200
b0 '
b1 #
b1 )
b0 %
0&
#210
1&
#220
b10 #
b10 )
1(
0&
#230
0!
b0 .
b10 +
1&
#240
b1 '
0&
#250
1&
#260
b10 '
0(
0&
#270
b1 .
1&
#280
b11 '
0&
#290
b10 .
b1 +
1&
#300
b100 '
0&
#310
b11 .
b0 +
1&
#320
b101 '
0&
#330
b100 .
1&
#340
b110 '
0&
#350
b101 .
1&
#360
b111 '
0&
#370
b110 .
1&
#380
b1000 '
0&
#390
b111 .
1&
#400
b1001 '
0&
#410
1!
1&
#420
b0 '
b11 #
b11 )
0&
#430
1&
#440
b100 #
b100 )
1(
0&
#450
0!
b0 .
b100 +
1&
#460
b1 '
0&
#470
1&
#480
b10 '
0(
0&
#490
b1 .
1&
#500
b11 '
0&
#510
b10 .
b10 +
1&
#520
b100 '
0&
#530
b11 .
b1 +
1&
#540
b101 '
0&
#550
b100 .
b0 +
1&
#560
b110 '
0&
#570
b101 .
1&
#580
b111 '
0&
#590
b110 .
1&
#600
b1000 '
0&
#610
b111 .
1&
#620
b1001 '
0&
#630
1!
1&
#640
b0 '
b101 #
b101 )
0&
#650
1&
#660
b110 #
b110 )
1(
0&
#670
0!
b0 .
b110 +
1&
#680
b1 '
0&
#690
1&
#700
b10 '
0(
0&
#710
b1 .
1&
#720
b11 '
0&
#730
b10 .
b11 +
1&
#740
b100 '
0&
#750
b11 .
b1 +
1&
#760
b101 '
0&
#770
b100 .
b0 +
1&
#780
b110 '
0&
#790
b101 .
1&
#800
b111 '
0&
#810
b110 .
1&
#820
b1000 '
0&
#830
b111 .
1&
#840
b1001 '
0&
#850
1!
1&
#860
b0 '
b111 #
b111 )
0&
#870
1&
#880
b1000 #
b1000 )
1(
0&
#890
0!
b0 .
b1000 +
1&
#900
b1 '
0&
#910
1&
#920
b10 '
0(
0&
#930
b1 .
1&
#940
b11 '
0&
#950
b10 .
b100 +
1&
#960
b100 '
0&
#970
b11 .
b10 +
1&
#980
b101 '
0&
#990
b100 .
b1 +
1&
#1000
b110 '
0&
#1010
b101 .
b0 +
1&
#1020
b111 '
0&
#1030
b110 .
1&
#1040
b1000 '
0&
#1050
b111 .
1&
#1060
b1001 '
0&
#1070
1!
1&
#1080
b0 '
b1001 #
b1001 )
0&
#1090
1&
#1100
b1010 #
b1010 )
1(
0&
#1110
0!
b0 .
b1010 +
1&
#1120
b1 '
0&
#1130
1&
#1140
b10 '
0(
0&
#1150
b1 .
1&
#1160
b11 '
0&
#1170
b10 .
b101 +
1&
#1180
b100 '
0&
#1190
b11 .
b10 +
1&
#1200
b101 '
0&
#1210
b100 .
b1 +
1&
#1220
b110 '
0&
#1230
b101 .
b0 +
1&
#1240
b111 '
0&
#1250
b110 .
1&
#1260
b1000 '
0&
#1270
b111 .
1&
#1280
b1001 '
0&
#1290
1!
1&
#1300
b0 '
b1011 #
b1011 )
0&
#1310
1&
#1320
b1100 #
b1100 )
1(
0&
#1330
0!
b0 .
b1100 +
1&
#1340
b1 '
0&
#1350
1&
#1360
b10 '
0(
0&
#1370
b1 .
1&
#1380
b11 '
0&
#1390
b10 .
b110 +
1&
#1400
b100 '
0&
#1410
b11 .
b11 +
1&
#1420
b101 '
0&
#1430
b100 .
b1 +
1&
#1440
b110 '
0&
#1450
b101 .
b0 +
1&
#1460
b111 '
0&
#1470
b110 .
1&
#1480
b1000 '
0&
#1490
b111 .
1&
#1500
b1001 '
0&
#1510
1!
1&
#1520
b0 '
b1101 #
b1101 )
0&
#1530
1&
#1540
b1110 #
b1110 )
1(
0&
#1550
0!
b0 .
b1110 +
1&
#1560
b1 '
0&
#1570
1&
#1580
b10 '
0(
0&
#1590
b1 .
1&
#1600
b11 '
0&
#1610
b10 .
b111 +
1&
#1620
b100 '
0&
#1630
b11 .
b11 +
1&
#1640
b101 '
0&
#1650
b100 .
b1 +
1&
#1660
b110 '
0&
#1670
b101 .
b0 +
1&
#1680
b111 '
0&
#1690
b110 .
1&
#1700
b1000 '
0&
#1710
b111 .
1&
#1720
b1001 '
0&
#1730
1!
1&
#1740
b0 '
b1111 #
b1111 )
0&
#1750
1&
#1760
b10000 #
b10000 )
1(
0&
#1770
0!
b0 .
b10000 +
1&
#1780
b1 '
0&
#1790
1&
#1800
b10 '
0(
0&
#1810
b1 .
1&
#1820
b11 '
0&
#1830
b10 .
b1000 +
1&
#1840
b100 '
0&
#1850
b11 .
b100 +
1&
#1860
b101 '
0&
#1870
b100 .
b10 +
1&
#1880
b110 '
0&
#1890
b101 .
b1 +
1&
#1900
b111 '
0&
#1910
b110 .
b0 +
1&
#1920
b1000 '
0&
#1930
b111 .
1&
#1940
b1001 '
0&
#1950
1!
1&
#1960
b0 '
b10001 #
b10001 )
0&
#1970
1&
#1980
b10010 #
b10010 )
1(
0&
#1990
0!
b0 .
b10010 +
1&
#2000
b1 '
0&
#2010
1&
#2020
b10 '
0(
0&
#2030
b1 .
1&
#2040
b11 '
0&
#2050
b10 .
b1001 +
1&
#2060
b100 '
0&
#2070
b11 .
b100 +
1&
#2080
b101 '
0&
#2090
b100 .
b10 +
1&
#2100
b110 '
0&
#2110
b101 .
b1 +
1&
#2120
b111 '
0&
#2130
b110 .
b0 +
1&
#2140
b1000 '
0&
#2150
b111 .
1&
#2160
b1001 '
0&
#2170
1!
1&
#2180
b0 '
b10011 #
b10011 )
0&
#2190
1&
#2200
b10100 #
b10100 )
1(
0&
#2210
0!
b0 .
b10100 +
1&
#2220
b1 '
0&
#2230
1&
#2240
b10 '
0(
0&
#2250
b1 .
1&
#2260
b11 '
0&
#2270
b10 .
b1010 +
1&
#2280
b100 '
0&
#2290
b11 .
b101 +
1&
#2300
b101 '
0&
#2310
b100 .
b10 +
1&
#2320
b110 '
0&
#2330
b101 .
b1 +
1&
#2340
b111 '
0&
#2350
b110 .
b0 +
1&
#2360
b1000 '
0&
#2370
b111 .
1&
#2380
b1001 '
0&
#2390
1!
1&
#2400
b0 '
b10101 #
b10101 )
0&
#2410
1&
#2420
b10110 #
b10110 )
1(
0&
#2430
0!
b0 .
b10110 +
1&
#2440
b1 '
0&
#2450
1&
#2460
b10 '
0(
0&
#2470
b1 .
1&
#2480
b11 '
0&
#2490
b10 .
b1011 +
1&
#2500
b100 '
0&
#2510
b11 .
b101 +
1&
#2520
b101 '
0&
#2530
b100 .
b10 +
1&
#2540
b110 '
0&
#2550
b101 .
b1 +
1&
#2560
b111 '
0&
#2570
b110 .
b0 +
1&
#2580
b1000 '
0&
#2590
b111 .
1&
#2600
b1001 '
0&
#2610
1!
1&
#2620
b0 '
b10111 #
b10111 )
0&
#2630
1&
#2640
b11000 #
b11000 )
1(
0&
#2650
0!
b0 .
b11000 +
1&
#2660
b1 '
0&
#2670
1&
#2680
b10 '
0(
0&
#2690
b1 .
1&
#2700
b11 '
0&
#2710
b10 .
b1100 +
1&
#2720
b100 '
0&
#2730
b11 .
b110 +
1&
#2740
b101 '
0&
#2750
b100 .
b11 +
1&
#2760
b110 '
0&
#2770
b101 .
b1 +
1&
#2780
b111 '
0&
#2790
b110 .
b0 +
1&
#2800
b1000 '
0&
#2810
b111 .
1&
#2820
b1001 '
0&
#2830
1!
1&
#2840
b0 '
b11001 #
b11001 )
0&
#2850
1&
#2860
b11010 #
b11010 )
1(
0&
#2870
0!
b0 .
b11010 +
1&
#2880
b1 '
0&
#2890
1&
#2900
b10 '
0(
0&
#2910
b1 .
1&
#2920
b11 '
0&
#2930
b10 .
b1101 +
1&
#2940
b100 '
0&
#2950
b11 .
b110 +
1&
#2960
b101 '
0&
#2970
b100 .
b11 +
1&
#2980
b110 '
0&
#2990
b101 .
b1 +
1&
#3000
b111 '
0&
#3010
b110 .
b0 +
1&
#3020
b1000 '
0&
#3030
b111 .
1&
#3040
b1001 '
0&
#3050
1!
1&
#3060
b0 '
b11011 #
b11011 )
0&
#3070
1&
#3080
b11100 #
b11100 )
1(
0&
#3090
0!
b0 .
b11100 +
1&
#3100
b1 '
0&
#3110
1&
#3120
b10 '
0(
0&
#3130
b1 .
1&
#3140
b11 '
0&
#3150
b10 .
b1110 +
1&
#3160
b100 '
0&
#3170
b11 .
b111 +
1&
#3180
b101 '
0&
#3190
b100 .
b11 +
1&
#3200
b110 '
0&
#3210
b101 .
b1 +
1&
#3220
b111 '
0&
#3230
b110 .
b0 +
1&
#3240
b1000 '
0&
#3250
b111 .
1&
#3260
b1001 '
0&
#3270
1!
1&
#3280
b0 '
b11101 #
b11101 )
0&
#3290
1&
#3300
b11110 #
b11110 )
1(
0&
#3310
0!
b0 .
b11110 +
1&
#3320
b1 '
0&
#3330
1&
#3340
b10 '
0(
0&
#3350
b1 .
1&
#3360
b11 '
0&
#3370
b10 .
b1111 +
1&
#3380
b100 '
0&
#3390
b11 .
b111 +
1&
#3400
b101 '
0&
#3410
b100 .
b11 +
1&
#3420
b110 '
0&
#3430
b101 .
b1 +
1&
#3440
b111 '
0&
#3450
b110 .
b0 +
1&
#3460
b1000 '
0&
#3470
b111 .
1&
#3480
b1001 '
0&
#3490
1!
1&
#3500
b0 '
b11111 #
b11111 )
0&
#3510
1&
#3520
b100000 #
b100000 )
1(
0&
#3530
0!
b0 .
b100000 +
1&
#3540
b1 '
0&
#3550
1&
#3560
b10 '
0(
0&
#3570
b1 .
1&
#3580
b11 '
0&
#3590
b10 .
b10000 +
1&
#3600
b100 '
0&
#3610
b11 .
b1000 +
1&
#3620
b101 '
0&
#3630
b100 .
b100 +
1&
#3640
b110 '
0&
#3650
b101 .
b10 +
1&
#3660
b111 '
0&
#3670
b110 .
b1 +
1&
#3680
b1000 '
0&
#3690
b111 .
b0 +
1&
#3700
b1001 '
0&
#3710
1!
1&
#3720
b0 '
b100001 #
b100001 )
0&
#3730
1&
#3740
b100010 #
b100010 )
1(
0&
#3750
0!
b0 .
b100010 +
1&
#3760
b1 '
0&
#3770
1&
#3780
b10 '
0(
0&
#3790
b1 .
1&
#3800
b11 '
0&
#3810
b10 .
b10001 +
1&
#3820
b100 '
0&
#3830
b11 .
b1000 +
1&
#3840
b101 '
0&
#3850
b100 .
b100 +
1&
#3860
b110 '
0&
#3870
b101 .
b10 +
1&
#3880
b111 '
0&
#3890
b110 .
b1 +
1&
#3900
b1000 '
0&
#3910
b111 .
b0 +
1&
#3920
b1001 '
0&
#3930
1!
1&
#3940
b0 '
b100011 #
b100011 )
0&
#3950
1&
#3960
b100100 #
b100100 )
1(
0&
#3970
0!
b0 .
b100100 +
1&
#3980
b1 '
0&
#3990
1&
#4000
b10 '
0(
0&
#4010
b1 .
1&
#4020
b11 '
0&
#4030
b10 .
b10010 +
1&
#4040
b100 '
0&
#4050
b11 .
b1001 +
1&
#4060
b101 '
0&
#4070
b100 .
b100 +
1&
#4080
b110 '
0&
#4090
b101 .
b10 +
1&
#4100
b111 '
0&
#4110
b110 .
b1 +
1&
#4120
b1000 '
0&
#4130
b111 .
b0 +
1&
#4140
b1001 '
0&
#4150
1!
1&
#4160
b0 '
b100101 #
b100101 )
0&
#4170
1&
#4180
b100110 #
b100110 )
1(
0&
#4190
0!
b0 .
b100110 +
1&
#4200
b1 '
0&
#4210
1&
#4220
b10 '
0(
0&
#4230
b1 .
1&
#4240
b11 '
0&
#4250
b10 .
b10011 +
1&
#4260
b100 '
0&
#4270
b11 .
b1001 +
1&
#4280
b101 '
0&
#4290
b100 .
b100 +
1&
#4300
b110 '
0&
#4310
b101 .
b10 +
1&
#4320
b111 '
0&
#4330
b110 .
b1 +
1&
#4340
b1000 '
0&
#4350
b111 .
b0 +
1&
#4360
b1001 '
0&
#4370
1!
1&
#4380
b0 '
b100111 #
b100111 )
0&
#4390
1&
#4400
b101000 #
b101000 )
1(
0&
#4410
0!
b0 .
b101000 +
1&
#4420
b1 '
0&
#4430
1&
#4440
b10 '
0(
0&
#4450
b1 .
1&
#4460
b11 '
0&
#4470
b10 .
b10100 +
1&
#4480
b100 '
0&
#4490
b11 .
b1010 +
1&
#4500
b101 '
0&
#4510
b100 .
b101 +
1&
#4520
b110 '
0&
#4530
b101 .
b10 +
1&
#4540
b111 '
0&
#4550
b110 .
b1 +
1&
#4560
b1000 '
0&
#4570
b111 .
b0 +
1&
#4580
b1001 '
0&
#4590
1!
1&
#4600
b0 '
b101001 #
b101001 )
0&
#4610
1&
#4620
b101010 #
b101010 )
1(
0&
#4630
0!
b0 .
b101010 +
1&
#4640
b1 '
0&
#4650
1&
#4660
b10 '
0(
0&
#4670
b1 .
1&
#4680
b11 '
0&
#4690
b10 .
b10101 +
1&
#4700
b100 '
0&
#4710
b11 .
b1010 +
1&
#4720
b101 '
0&
#4730
b100 .
b101 +
1&
#4740
b110 '
0&
#4750
b101 .
b10 +
1&
#4760
b111 '
0&
#4770
b110 .
b1 +
1&
#4780
b1000 '
0&
#4790
b111 .
b0 +
1&
#4800
b1001 '
0&
#4810
1!
1&
#4820
b0 '
b101011 #
b101011 )
0&
#4830
1&
#4840
b101100 #
b101100 )
1(
0&
#4850
0!
b0 .
b101100 +
1&
#4860
b1 '
0&
#4870
1&
#4880
b10 '
0(
0&
#4890
b1 .
1&
#4900
b11 '
0&
#4910
b10 .
b10110 +
1&
#4920
b100 '
0&
#4930
b11 .
b1011 +
1&
#4940
b101 '
0&
#4950
b100 .
b101 +
1&
#4960
b110 '
0&
#4970
b101 .
b10 +
1&
#4980
b111 '
0&
#4990
b110 .
b1 +
1&
#5000
b1000 '
0&
#5010
b111 .
b0 +
1&
#5020
b1001 '
0&
#5030
1!
1&
#5040
b0 '
b101101 #
b101101 )
0&
#5050
1&
#5060
b101110 #
b101110 )
1(
0&
#5070
0!
b0 .
b101110 +
1&
#5080
b1 '
0&
#5090
1&
#5100
b10 '
0(
0&
#5110
b1 .
1&
#5120
b11 '
0&
#5130
b10 .
b10111 +
1&
#5140
b100 '
0&
#5150
b11 .
b1011 +
1&
#5160
b101 '
0&
#5170
b100 .
b101 +
1&
#5180
b110 '
0&
#5190
b101 .
b10 +
1&
#5200
b111 '
0&
#5210
b110 .
b1 +
1&
#5220
b1000 '
0&
#5230
b111 .
b0 +
1&
#5240
b1001 '
0&
#5250
1!
1&
#5260
b0 '
b101111 #
b101111 )
0&
#5270
1&
#5280
b110000 #
b110000 )
1(
0&
#5290
0!
b0 .
b110000 +
1&
#5300
b1 '
0&
#5310
1&
#5320
b10 '
0(
0&
#5330
b1 .
1&
#5340
b11 '
0&
#5350
b10 .
b11000 +
1&
#5360
b100 '
0&
#5370
b11 .
b1100 +
1&
#5380
b101 '
0&
#5390
b100 .
b110 +
1&
#5400
b110 '
0&
#5410
b101 .
b11 +
1&
#5420
b111 '
0&
#5430
b110 .
b1 +
1&
#5440
b1000 '
0&
#5450
b111 .
b0 +
1&
#5460
b1001 '
0&
#5470
1!
1&
#5480
b0 '
b110001 #
b110001 )
0&
#5490
1&
#5500
b110010 #
b110010 )
1(
0&
#5510
0!
b0 .
b110010 +
1&
#5520
b1 '
0&
#5530
1&
#5540
b10 '
0(
0&
#5550
b1 .
1&
#5560
b11 '
0&
#5570
b10 .
b11001 +
1&
#5580
b100 '
0&
#5590
b11 .
b1100 +
1&
#5600
b101 '
0&
#5610
b100 .
b110 +
1&
#5620
b110 '
0&
#5630
b101 .
b11 +
1&
#5640
b111 '
0&
#5650
b110 .
b1 +
1&
#5660
b1000 '
0&
#5670
b111 .
b0 +
1&
#5680
b1001 '
0&
#5690
1!
1&
#5700
b0 '
b110011 #
b110011 )
0&
#5710
1&
#5720
b110100 #
b110100 )
1(
0&
#5730
0!
b0 .
b110100 +
1&
#5740
b1 '
0&
#5750
1&
#5760
b10 '
0(
0&
#5770
b1 .
1&
#5780
b11 '
0&
#5790
b10 .
b11010 +
1&
#5800
b100 '
0&
#5810
b11 .
b1101 +
1&
#5820
b101 '
0&
#5830
b100 .
b110 +
1&
#5840
b110 '
0&
#5850
b101 .
b11 +
1&
#5860
b111 '
0&
#5870
b110 .
b1 +
1&
#5880
b1000 '
0&
#5890
b111 .
b0 +
1&
#5900
b1001 '
0&
#5910
1!
1&
#5920
b0 '
b110101 #
b110101 )
0&
#5930
1&
#5940
b110110 #
b110110 )
1(
0&
#5950
0!
b0 .
b110110 +
1&
#5960
b1 '
0&
#5970
1&
#5980
b10 '
0(
0&
#5990
b1 .
1&
#6000
b11 '
0&
#6010
b10 .
b11011 +
1&
#6020
b100 '
0&
#6030
b11 .
b1101 +
1&
#6040
b101 '
0&
#6050
b100 .
b110 +
1&
#6060
b110 '
0&
#6070
b101 .
b11 +
1&
#6080
b111 '
0&
#6090
b110 .
b1 +
1&
#6100
b1000 '
0&
#6110
b111 .
b0 +
1&
#6120
b1001 '
0&
#6130
1!
1&
#6140
b0 '
b110111 #
b110111 )
0&
#6150
1&
#6160
b111000 #
b111000 )
1(
0&
#6170
0!
b0 .
b111000 +
1&
#6180
b1 '
0&
#6190
1&
#6200
b10 '
0(
0&
#6210
b1 .
1&
#6220
b11 '
0&
#6230
b10 .
b11100 +
1&
#6240
b100 '
0&
#6250
b11 .
b1110 +
1&
#6260
b101 '
0&
#6270
b100 .
b111 +
1&
#6280
b110 '
0&
#6290
b101 .
b11 +
1&
#6300
b111 '
0&
#6310
b110 .
b1 +
1&
#6320
b1000 '
0&
#6330
b111 .
b0 +
1&
#6340
b1001 '
0&
#6350
1!
1&
#6360
b0 '
b111001 #
b111001 )
0&
#6370
1&
#6380
b111010 #
b111010 )
1(
0&
#6390
0!
b0 .
b111010 +
1&
#6400
b1 '
0&
#6410
1&
#6420
b10 '
0(
0&
#6430
b1 .
1&
#6440
b11 '
0&
#6450
b10 .
b11101 +
1&
#6460
b100 '
0&
#6470
b11 .
b1110 +
1&
#6480
b101 '
0&
#6490
b100 .
b111 +
1&
#6500
b110 '
0&
#6510
b101 .
b11 +
1&
#6520
b111 '
0&
#6530
b110 .
b1 +
1&
#6540
b1000 '
0&
#6550
b111 .
b0 +
1&
#6560
b1001 '
0&
#6570
1!
1&
#6580
b0 '
b111011 #
b111011 )
0&
#6590
1&
#6600
b111100 #
b111100 )
1(
0&
#6610
0!
b0 .
b111100 +
1&
#6620
b1 '
0&
#6630
1&
#6640
b10 '
0(
0&
#6650
b1 .
1&
#6660
b11 '
0&
#6670
b10 .
b11110 +
1&
#6680
b100 '
0&
#6690
b11 .
b1111 +
1&
#6700
b101 '
0&
#6710
b100 .
b111 +
1&
#6720
b110 '
0&
#6730
b101 .
b11 +
1&
#6740
b111 '
0&
#6750
b110 .
b1 +
1&
#6760
b1000 '
0&
#6770
b111 .
b0 +
1&
#6780
b1001 '
0&
#6790
1!
1&
#6800
b0 '
b111101 #
b111101 )
0&
#6810
1&
#6820
b111110 #
b111110 )
1(
0&
#6830
0!
b0 .
b111110 +
1&
#6840
b1 '
0&
#6850
1&
#6860
b10 '
0(
0&
#6870
b1 .
1&
#6880
b11 '
0&
#6890
b10 .
b11111 +
1&
#6900
b100 '
0&
#6910
b11 .
b1111 +
1&
#6920
b101 '
0&
#6930
b100 .
b111 +
1&
#6940
b110 '
0&
#6950
b101 .
b11 +
1&
#6960
b111 '
0&
#6970
b110 .
b1 +
1&
#6980
b1000 '
0&
#6990
b111 .
b0 +
1&
#7000
b1001 '
0&
#7010
1!
1&
#7020
b0 '
b111111 #
b111111 )
0&
#7030
1&
#7040
b1000000 #
b1000000 )
1(
0&
#7050
0!
b0 .
b1000000 +
1&
#7060
b1 '
0&
#7070
1&
#7080
b10 '
0(
0&
#7090
b1 .
1&
#7100
b11 '
0&
#7110
b10 .
b100000 +
1&
#7120
b100 '
0&
#7130
b11 .
b10000 +
1&
#7140
b101 '
0&
#7150
b100 .
b1000 +
1&
#7160
b110 '
0&
#7170
b101 .
b100 +
1&
#7180
b111 '
0&
#7190
b110 .
b10 +
1&
#7200
b1000 '
0&
#7210
b111 .
b1 +
1&
#7220
b1001 '
0&
#7230
1!
1&
#7240
b0 '
b1000001 #
b1000001 )
0&
#7250
1&
#7260
b1000010 #
b1000010 )
1(
0&
#7270
0!
b0 .
b1000010 +
1&
#7280
b1 '
0&
#7290
1&
#7300
b10 '
0(
0&
#7310
b1 .
1&
#7320
b11 '
0&
#7330
b10 .
b100001 +
1&
#7340
b100 '
0&
#7350
b11 .
b10000 +
1&
#7360
b101 '
0&
#7370
b100 .
b1000 +
1&
#7380
b110 '
0&
#7390
b101 .
b100 +
1&
#7400
b111 '
0&
#7410
b110 .
b10 +
1&
#7420
b1000 '
0&
#7430
b111 .
b1 +
1&
#7440
b1001 '
0&
#7450
1!
1&
#7460
b0 '
b1000011 #
b1000011 )
0&
#7470
1&
#7480
b1000100 #
b1000100 )
1(
0&
#7490
0!
b0 .
b1000100 +
1&
#7500
b1 '
0&
#7510
1&
#7520
b10 '
0(
0&
#7530
b1 .
1&
#7540
b11 '
0&
#7550
b10 .
b100010 +
1&
#7560
b100 '
0&
#7570
b11 .
b10001 +
1&
#7580
b101 '
0&
#7590
b100 .
b1000 +
1&
#7600
b110 '
0&
#7610
b101 .
b100 +
1&
#7620
b111 '
0&
#7630
b110 .
b10 +
1&
#7640
b1000 '
0&
#7650
b111 .
b1 +
1&
#7660
b1001 '
0&
#7670
1!
1&
#7680
b0 '
b1000101 #
b1000101 )
0&
#7690
1&
#7700
b1000110 #
b1000110 )
1(
0&
#7710
0!
b0 .
b1000110 +
1&
#7720
b1 '
0&
#7730
1&
#7740
b10 '
0(
0&
#7750
b1 .
1&
#7760
b11 '
0&
#7770
b10 .
b100011 +
1&
#7780
b100 '
0&
#7790
b11 .
b10001 +
1&
#7800
b101 '
0&
#7810
b100 .
b1000 +
1&
#7820
b110 '
0&
#7830
b101 .
b100 +
1&
#7840
b111 '
0&
#7850
b110 .
b10 +
1&
#7860
b1000 '
0&
#7870
b111 .
b1 +
1&
#7880
b1001 '
0&
#7890
1!
1&
#7900
b0 '
b1000111 #
b1000111 )
0&
#7910
1&
#7920
b1001000 #
b1001000 )
1(
0&
#7930
0!
b0 .
b1001000 +
1&
#7940
b1 '
0&
#7950
1&
#7960
b10 '
0(
0&
#7970
b1 .
1&
#7980
b11 '
0&
#7990
b10 .
b100100 +
1&
#8000
b100 '
0&
#8010
b11 .
b10010 +
1&
#8020
b101 '
0&
#8030
b100 .
b1001 +
1&
#8040
b110 '
0&
#8050
b101 .
b100 +
1&
#8060
b111 '
0&
#8070
b110 .
b10 +
1&
#8080
b1000 '
0&
#8090
b111 .
b1 +
1&
#8100
b1001 '
0&
#8110
1!
1&
#8120
b0 '
b1001001 #
b1001001 )
0&
#8130
1&
#8140
b1001010 #
b1001010 )
1(
0&
#8150
0!
b0 .
b1001010 +
1&
#8160
b1 '
0&
#8170
1&
#8180
b10 '
0(
0&
#8190
b1 .
1&
#8200
b11 '
0&
#8210
b10 .
b100101 +
1&
#8220
b100 '
0&
#8230
b11 .
b10010 +
1&
#8240
b101 '
0&
#8250
b100 .
b1001 +
1&
#8260
b110 '
0&
#8270
b101 .
b100 +
1&
#8280
b111 '
0&
#8290
b110 .
b10 +
1&
#8300
b1000 '
0&
#8310
b111 .
b1 +
1&
#8320
b1001 '
0&
#8330
1!
1&
#8340
b0 '
b1001011 #
b1001011 )
0&
#8350
1&
#8360
b1001100 #
b1001100 )
1(
0&
#8370
0!
b0 .
b1001100 +
1&
#8380
b1 '
0&
#8390
1&
#8400
b10 '
0(
0&
#8410
b1 .
1&
#8420
b11 '
0&
#8430
b10 .
b100110 +
1&
#8440
b100 '
0&
#8450
b11 .
b10011 +
1&
#8460
b101 '
0&
#8470
b100 .
b1001 +
1&
#8480
b110 '
0&
#8490
b101 .
b100 +
1&
#8500
b111 '
0&
#8510
b110 .
b10 +
1&
#8520
b1000 '
0&
#8530
b111 .
b1 +
1&
#8540
b1001 '
0&
#8550
1!
1&
#8560
b0 '
b1001101 #
b1001101 )
0&
#8570
1&
#8580
b1001110 #
b1001110 )
1(
0&
#8590
0!
b0 .
b1001110 +
1&
#8600
b1 '
0&
#8610
1&
#8620
b10 '
0(
0&
#8630
b1 .
1&
#8640
b11 '
0&
#8650
b10 .
b100111 +
1&
#8660
b100 '
0&
#8670
b11 .
b10011 +
1&
#8680
b101 '
0&
#8690
b100 .
b1001 +
1&
#8700
b110 '
0&
#8710
b101 .
b100 +
1&
#8720
b111 '
0&
#8730
b110 .
b10 +
1&
#8740
b1000 '
0&
#8750
b111 .
b1 +
1&
#8760
b1001 '
0&
#8770
1!
1&
#8780
b0 '
b1001111 #
b1001111 )
0&
#8790
1&
#8800
b1010000 #
b1010000 )
1(
0&
#8810
0!
b0 .
b1010000 +
1&
#8820
b1 '
0&
#8830
1&
#8840
b10 '
0(
0&
#8850
b1 .
1&
#8860
b11 '
0&
#8870
b10 .
b101000 +
1&
#8880
b100 '
0&
#8890
b11 .
b10100 +
1&
#8900
b101 '
0&
#8910
b100 .
b1010 +
1&
#8920
b110 '
0&
#8930
b101 .
b101 +
1&
#8940
b111 '
0&
#8950
b110 .
b10 +
1&
#8960
b1000 '
0&
#8970
b111 .
b1 +
1&
#8980
b1001 '
0&
#8990
1!
1&
#9000
b0 '
b1010001 #
b1010001 )
0&
#9010
1&
#9020
b1010010 #
b1010010 )
1(
0&
#9030
0!
b0 .
b1010010 +
1&
#9040
b1 '
0&
#9050
1&
#9060
b10 '
0(
0&
#9070
b1 .
1&
#9080
b11 '
0&
#9090
b10 .
b101001 +
1&
#9100
b100 '
0&
#9110
b11 .
b10100 +
1&
#9120
b101 '
0&
#9130
b100 .
b1010 +
1&
#9140
b110 '
0&
#9150
b101 .
b101 +
1&
#9160
b111 '
0&
#9170
b110 .
b10 +
1&
#9180
b1000 '
0&
#9190
b111 .
b1 +
1&
#9200
b1001 '
0&
#9210
1!
1&
#9220
b0 '
b1010011 #
b1010011 )
0&
#9230
1&
#9240
b1010100 #
b1010100 )
1(
0&
#9250
0!
b0 .
b1010100 +
1&
#9260
b1 '
0&
#9270
1&
#9280
b10 '
0(
0&
#9290
b1 .
1&
#9300
b11 '
0&
#9310
b10 .
b101010 +
1&
#9320
b100 '
0&
#9330
b11 .
b10101 +
1&
#9340
b101 '
0&
#9350
b100 .
b1010 +
1&
#9360
b110 '
0&
#9370
b101 .
b101 +
1&
#9380
b111 '
0&
#9390
b110 .
b10 +
1&
#9400
b1000 '
0&
#9410
b111 .
b1 +
1&
#9420
b1001 '
0&
#9430
1!
1&
#9440
b0 '
b1010101 #
b1010101 )
0&
#9450
1&
